bounds/__init__.py
bounds/_realtransforms_autograd.py
bounds/_realtransforms_from_fft.py
bounds/_utils.py
bounds/_version.py
bounds/indexing.py
bounds/padding.py
bounds/realtransforms.py
bounds/types.py
torch_bounds-0.1.1.dist-info/LICENSE
torch_bounds-0.1.1.dist-info/LICENSE-CUPY
torch_bounds-0.1.1.dist-info/METADATA
torch_bounds-0.1.1.dist-info/WHEEL
torch_bounds-0.1.1.dist-info/top_level.txt
torch_bounds-0.1.1.dist-info/RECORD
