Metadata-Version: 2.1
Name: torch-bounds
Version: 0.1.1
Summary: Boundary conditions and real transforms in PyTorch
Author-email: Yael Balbastre <yael.balbastre@gmail.com>
License: MIT License
Project-URL: Homepage, https://github.com/balbasty/torch-bounds
Project-URL: Issues, https://github.com/balbasty/torch-bounds/issues
Classifier: License :: OSI Approved :: MIT License
Classifier: Operating System :: OS Independent
Classifier: Programming Language :: Python :: 3
Classifier: Intended Audience :: Science/Research
Classifier: Topic :: Scientific/Engineering :: Artificial Intelligence
Requires-Python: >=3.6
License-File: LICENSE
License-File: LICENSE-CUPY
Requires-Dist: torch >=1.3
Provides-Extra: realtransforms
Requires-Dist: torch >=1.8 ; extra == 'realtransforms'
Provides-Extra: test
Requires-Dist: scipy ; extra == 'test'
